[
    {
        "id": 1,
        "nomape": "Familia Franco",
        "nomusu": "famfran",
        "email": "familia@franco.com",
        "fecha": "1992-09-25",
        "dom": "A. del valle 1553",
        "perfil": "vend",
        "categorias": [
            "hog",
            "jug"
        ],
        "foto": "user-1664919993070.jpeg",
        "contra": "$2a$10$kjlSxUiL8U3nNU64vx8ghuAVaE9mA/ivpYsxnkfkLgnCueju8fRf6",
        "confirmar": "$2a$10$sXy9wERL8kKDX/ElgkwPS.N/yjlUiUQtNsx75/HyuxgY0JTk7OL3e"
    },
    {
        "id": 2,
        "nomape": "Bernardo Franco",
        "nomusu": "berniifranco",
        "email": "berniifranco@gmail.com",
        "fecha": "1992-09-25",
        "dom": "Pi y Margall 420",
        "perfil": "comp",
        "categorias": [
            "elec",
            "jug"
        ],
        "foto": "user-1664922743960.jpeg",
        "contra": "$2a$10$f2j6KIXmyd9.Ot8MkwRYLOBFSiLHZy659vzM5DkQaeaqtnRosfR6C",
        "confirmar": "$2a$10$FOxmzygX9h17fyuyLOeL6OO/1k.30g3cP295sae/VnXtRJD3oDV2q"
    },
    {
        "id": 3,
        "nomape": "Metallica",
        "nomusu": "metallica",
        "email": "metallica@gmail.com",
        "fecha": "2022-04-30",
        "dom": "av. del libertador 4000",
        "perfil": "vend",
        "categorias": [
            "elec",
            "moda",
            "hog",
            "jug",
            "vida"
        ],
        "foto": "user-1664926561402.jpg",
        "contra": "$2a$10$bDIx1n5uvt3nFQ.LTgbcCu5Me8c/8BT4G7e8Abu2K6V8G.axzKc.K",
        "confirmar": "$2a$10$JSLWqRPAzHEMLDqO1ERqs.iKrhB1rzjnH9xhr5Wv0dpXQP9Jblhk."
    }
]